{"https://github.com/indoorequal/indoorequal.org.git#":{"drift":0,"pulse":43.24982888432581,"date":"2024-12-16T07:22:25.013Z"},"https://github.com/indoorequal/maplibre-gl-indoorequal.git#":{"drift":0,"pulse":7.468856947296373,"date":"2024-12-16T07:22:29.348Z"},"https://github.com/indoorequal/openlayers-indoorequal.git#":{"drift":0,"pulse":4.574948665297741,"date":"2024-12-16T07:22:33.647Z"},"https://github.com/indoorequal/parcel-transformer-markdown-front-matter.git#":{"drift":0.07392197125256673,"pulse":5.804243668720055,"date":"2024-12-16T07:22:37.780Z"},"https://github.com/indoorequal/vue-maplibre-gl.git#":{"drift":-0.38329911019849416,"pulse":14.765229295003422,"date":"2024-12-16T07:22:46.821Z"}}