{"https://github.com/indoorequal/indoorequal.org.git#":{"drift":4.599683771740692,"pulse":47.475307501180716,"date":"2025-11-14T07:22:05.805Z"},"https://github.com/indoorequal/maplibre-gl-indoorequal.git#":{"drift":2.4476888642477257,"pulse":7.9919505533994535,"date":"2025-11-14T07:22:06.715Z"},"https://github.com/indoorequal/openlayers-indoorequal.git#":{"drift":0.005475814013977016,"pulse":4.698248423992279,"date":"2025-11-14T07:22:07.807Z"},"https://github.com/indoorequal/parcel-transformer-markdown-front-matter.git#":{"drift":0,"pulse":7.04463472898143,"date":"2025-11-14T07:22:09.116Z"},"https://github.com/indoorequal/vue-maplibre-gl.git#":{"drift":1.1471830359281847,"pulse":20.400145109071367,"date":"2025-11-14T07:22:11.573Z"}}