{"https://github.com/indoorequal/indoorequal.org.git#":{"drift":1.478469783773794,"pulse":48.0283647165924,"date":"2025-09-03T07:20:26.756Z"},"https://github.com/indoorequal/maplibre-gl-indoorequal.git#":{"drift":1.7467846704586676,"pulse":10.064546157689753,"date":"2025-09-03T07:20:27.816Z"},"https://github.com/indoorequal/openlayers-indoorequal.git#":{"drift":0.35592791090850595,"pulse":7.293784266617384,"date":"2025-09-03T07:20:28.662Z"},"https://github.com/indoorequal/parcel-transformer-markdown-front-matter.git#":{"drift":0.024641163062896567,"pulse":6.5928800728283266,"date":"2025-09-03T07:20:29.910Z"},"https://github.com/indoorequal/vue-maplibre-gl.git#":{"drift":0.4544925631600923,"pulse":18.456231134109526,"date":"2025-09-03T07:20:31.796Z"}}