{"https://github.com/indoorequal/indoorequal.org.git#":{"drift":0.5585330294256555,"pulse":50.593783582140624,"date":"2026-06-04T10:39:45.184Z"},"https://github.com/indoorequal/maplibre-gl-indoorequal.git#":{"drift":0.05475814013977015,"pulse":8.659999863104648,"date":"2026-06-04T10:39:45.952Z"},"https://github.com/indoorequal/openlayers-indoorequal.git#":{"drift":1.941176067954852,"pulse":4.134239580552646,"date":"2026-06-04T10:39:46.875Z"},"https://github.com/indoorequal/parcel-transformer-markdown-front-matter.git#":{"drift":0.04654441911880463,"pulse":9.544343826361938,"date":"2026-06-04T10:39:47.878Z"},"https://github.com/indoorequal/vue-maplibre-gl.git#":{"drift":1.4702560627528287,"pulse":22.37965187512406,"date":"2026-06-04T10:39:50.317Z"}}