{"https://github.com/indoorequal/indoorequal.org.git#":{"drift":0,"pulse":51.483603359411894,"date":"2025-10-19T07:18:24.229Z"},"https://github.com/indoorequal/maplibre-gl-indoorequal.git#":{"drift":1.7604742054936104,"pulse":8.416326139482672,"date":"2025-10-19T07:18:25.095Z"},"https://github.com/indoorequal/openlayers-indoorequal.git#":{"drift":2.390192817100967,"pulse":5.336180756620602,"date":"2025-10-19T07:18:25.985Z"},"https://github.com/indoorequal/parcel-transformer-markdown-front-matter.git#":{"drift":0.027379070069885075,"pulse":7.1267719391910855,"date":"2025-10-19T07:18:26.946Z"},"https://github.com/indoorequal/vue-maplibre-gl.git#":{"drift":0.19439139749618403,"pulse":20.328959526889665,"date":"2025-10-19T07:18:28.864Z"}}