[{"dependency":"@babel/core","drift":0,"pulse":0.03559206023271732,"releases":0,"major":0,"minor":0,"patch":0,"available":"8.0.0-alpha.17"},{"dependency":"@babel/preset-env","drift":0,"pulse":0.019164955509924708,"releases":0,"major":0,"minor":0,"patch":0,"available":"8.0.0-alpha.17"},{"dependency":"@indoorequal/spritezero-cli","drift":0,"pulse":2.2477754962354553,"releases":0,"major":0,"minor":0,"patch":0,"available":"N/A"},{"dependency":"@rollup/plugin-babel","drift":0,"pulse":1.6043805612594113,"releases":0,"major":0,"minor":0,"patch":0,"available":"N/A"},{"dependency":"@rollup/plugin-commonjs","drift":0,"pulse":0.1861738535249829,"releases":0,"major":0,"minor":0,"patch":0,"available":"N/A"},{"dependency":"@rollup/plugin-node-resolve","drift":0,"pulse":0.17248459958932238,"releases":0,"major":0,"minor":0,"patch":0,"available":"N/A"},{"dependency":"@rollup/plugin-terser","drift":0,"pulse":1.6043805612594113,"releases":0,"major":0,"minor":0,"patch":0,"available":"N/A"},{"dependency":"array-equal","drift":1.3908281998631074,"pulse":0.09582477754962354,"releases":1,"major":1,"minor":0,"patch":0,"available":"2.0.0"},{"dependency":"babel-jest","drift":0,"pulse":0.28199863107460643,"releases":0,"major":0,"minor":0,"patch":0,"available":"30.0.0-alpha.7"},{"dependency":"debounce","drift":0,"pulse":0.5776865160848734,"releases":0,"major":0,"minor":0,"patch":0,"available":"N/A"},{"dependency":"documentation","drift":0,"pulse":1.2840520191649556,"releases":0,"major":0,"minor":0,"patch":0,"available":"N/A"},{"dependency":"jest-environment-jsdom","drift":0,"pulse":0.28199863107460643,"releases":0,"major":0,"minor":0,"patch":0,"available":"30.0.0-alpha.7"},{"dependency":"jest","drift":0,"pulse":0.28199863107460643,"releases":0,"major":0,"minor":0,"patch":0,"available":"30.0.0-alpha.7"},{"dependency":"rollup","drift":0,"pulse":0.019164955509924708,"releases":0,"major":0,"minor":0,"patch":0,"available":"N/A"}]