[{"dependency":"@parcel/packager-ts","drift":0,"pulse":0.28474232872680477,"releases":0,"major":0,"minor":0,"patch":0},{"dependency":"@parcel/plugin","drift":0,"pulse":0.28474232872680477,"releases":0,"major":0,"minor":0,"patch":0},{"dependency":"@parcel/transformer-typescript-types","drift":0,"pulse":0.28474232872680477,"releases":0,"major":0,"minor":0,"patch":0},{"dependency":"@types/yaml-front-matter","drift":0,"pulse":2.524350260443404,"releases":0,"major":0,"minor":0,"patch":0},{"dependency":"marked","drift":0,"pulse":0.043806512111816125,"releases":0,"major":0,"minor":0,"patch":0},{"dependency":"parcel","drift":0,"pulse":0.28474232872680477,"releases":0,"major":0,"minor":0,"patch":0},{"dependency":"typescript","drift":0,"pulse":0.08487511721664373,"releases":0,"major":0,"minor":0,"patch":0},{"dependency":"yaml-front-matter","drift":0,"pulse":5.426531687851222,"releases":0,"major":0,"minor":0,"patch":0}]