[{"dependency":"@babel/core","drift":0.13415468856947296,"pulse":0.05475701574264202,"releases":1,"major":0,"minor":1,"patch":0,"available":"7.27.1"},{"dependency":"@babel/preset-env","drift":0.22176591375770022,"pulse":0.038329911019849415,"releases":2,"major":0,"minor":1,"patch":1,"available":"7.27.2"},{"dependency":"@indoorequal/vue-maplibre-gl","drift":0,"pulse":0.1697467488021903,"releases":0,"major":0,"minor":0,"patch":0,"available":"N/A"},{"dependency":"@mdi/js","drift":0,"pulse":1.3990417522245038,"releases":0,"major":0,"minor":0,"patch":0,"available":"N/A"},{"dependency":"@parcel/optimizer-data-url","drift":0.14510609171800137,"pulse":0,"releases":4,"major":0,"minor":1,"patch":3,"available":"2.15.1"},{"dependency":"@parcel/resolver-glob","drift":0.14510609171800137,"pulse":0,"releases":4,"major":0,"minor":1,"patch":3,"available":"2.15.1"},{"dependency":"@parcel/transformer-inline-string","drift":0.14510609171800137,"pulse":0,"releases":4,"major":0,"minor":1,"patch":3,"available":"2.15.1"},{"dependency":"@parcel/transformer-sass","drift":0.14510609171800137,"pulse":0,"releases":4,"major":0,"minor":1,"patch":3,"available":"2.15.1"},{"dependency":"@parcel/transformer-vue","drift":0.14510609171800137,"pulse":0,"releases":4,"major":0,"minor":1,"patch":3,"available":"2.15.1"},{"dependency":"@turf/bbox","drift":0,"pulse":0.3915126625598905,"releases":0,"major":0,"minor":0,"patch":0,"available":"N/A"},{"dependency":"@turf/center-of-mass","drift":0,"pulse":0.3915126625598905,"releases":0,"major":0,"minor":0,"patch":0,"available":"N/A"},{"dependency":"@turf/line-to-polygon","drift":0,"pulse":0.3915126625598905,"releases":0,"major":0,"minor":0,"patch":0,"available":"N/A"},{"dependency":"@vue/test-utils","drift":0,"pulse":1.0376454483230664,"releases":0,"major":0,"minor":0,"patch":0,"available":"N/A"},{"dependency":"@vue/vue3-jest","drift":0,"pulse":1.702943189596167,"releases":0,"major":0,"minor":0,"patch":0,"available":"N/A"},{"dependency":"babel-jest","drift":0,"pulse":0.30116358658453113,"releases":0,"major":0,"minor":0,"patch":0,"available":"30.0.0-alpha.7"},{"dependency":"buffer","drift":0,"pulse":4.490075290896646,"releases":0,"major":0,"minor":0,"patch":0,"available":"N/A"},{"dependency":"dayjs","drift":0,"pulse":0.7474332648870636,"releases":0,"major":0,"minor":0,"patch":0,"available":"2.0.0-alpha.4"},{"dependency":"deepmerge","drift":0,"pulse":2.1793292265571527,"releases":0,"major":0,"minor":0,"patch":0,"available":"N/A"},{"dependency":"deepsortobj","drift":0,"pulse":3.5455167693360714,"releases":0,"major":0,"minor":0,"patch":0,"available":"N/A"},{"dependency":"jest-cli","drift":0,"pulse":0.30116358658453113,"releases":0,"major":0,"minor":0,"patch":0,"available":"30.0.0-alpha.7"},{"dependency":"jest-environment-jsdom","drift":0,"pulse":0.30116358658453113,"releases":0,"major":0,"minor":0,"patch":0,"available":"30.0.0-alpha.7"},{"dependency":"js-yaml","drift":0,"pulse":4.098562628336755,"releases":0,"major":0,"minor":0,"patch":0,"available":"N/A"},{"dependency":"jszip","drift":0,"pulse":2.7980835044490076,"releases":0,"major":0,"minor":0,"patch":0,"available":"N/A"},{"dependency":"lodash.uniq","drift":0,"pulse":8.766598220396988,"releases":0,"major":0,"minor":0,"patch":0,"available":"N/A"},{"dependency":"maplibre-gl-indoorequal","drift":0,"pulse":0.3750855578370979,"releases":0,"major":0,"minor":0,"patch":0,"available":"N/A"},{"dependency":"maplibre-gl","drift":0.17248459958932238,"pulse":0.038329911019849415,"releases":4,"major":0,"minor":3,"patch":1,"available":"5.5.0"},{"dependency":"opening_hours","drift":0,"pulse":3.0061601642710474,"releases":0,"major":0,"minor":0,"patch":0,"available":"N/A"},{"dependency":"osm2geojson-lite","drift":0,"pulse":0.17248459958932238,"releases":0,"major":0,"minor":0,"patch":0,"available":"N/A"},{"dependency":"parcel-reporter-static-files-copy","drift":0,"pulse":1.6646132785763177,"releases":0,"major":0,"minor":0,"patch":0,"available":"N/A"},{"dependency":"parcel-transformer-markdown-front-matter","drift":0,"pulse":1.0376454483230664,"releases":0,"major":0,"minor":0,"patch":0,"available":"N/A"},{"dependency":"parcel","drift":0.14510609171800137,"pulse":0,"releases":4,"major":0,"minor":1,"patch":3,"available":"2.15.1"},{"dependency":"process","drift":0,"pulse":8.06570841889117,"releases":0,"major":0,"minor":0,"patch":0,"available":"N/A"},{"dependency":"svgo","drift":0,"pulse":0.038329911019849415,"releases":0,"major":0,"minor":0,"patch":0,"available":"4.0.0-rc.4"},{"dependency":"vue-i18n","drift":0.07939767282683094,"pulse":0.12320328542094455,"releases":1,"major":0,"minor":0,"patch":1,"available":"11.1.3"},{"dependency":"vue","drift":0.4928131416837782,"pulse":0.01642710472279261,"releases":1,"major":0,"minor":0,"patch":1,"available":"3.5.14"},{"dependency":"vuetify","drift":0.17248459958932238,"pulse":0,"releases":8,"major":0,"minor":1,"patch":7,"available":"3.8.6"}]