[{"dependency":"@babel/core","drift":0,"pulse":0.09034907597535935,"releases":0,"major":0,"minor":0,"patch":0,"available":"8.0.0-alpha.14"},{"dependency":"@babel/preset-env","drift":0,"pulse":0.09034907597535935,"releases":0,"major":0,"minor":0,"patch":0,"available":"8.0.0-alpha.14"},{"dependency":"@indoorequal/vue-maplibre-gl","drift":0,"pulse":0.010951403148528405,"releases":0,"major":0,"minor":0,"patch":0,"available":"N/A"},{"dependency":"@mdi/js","drift":0,"pulse":1.0376454483230664,"releases":0,"major":0,"minor":0,"patch":0,"available":"N/A"},{"dependency":"@parcel/optimizer-data-url","drift":0,"pulse":0.0027378507871321013,"releases":0,"major":0,"minor":0,"patch":0,"available":"N/A"},{"dependency":"@parcel/resolver-glob","drift":0,"pulse":0.0027378507871321013,"releases":0,"major":0,"minor":0,"patch":0,"available":"2.13.4-canary.3393"},{"dependency":"@parcel/transformer-inline-string","drift":0,"pulse":0.0027378507871321013,"releases":0,"major":0,"minor":0,"patch":0,"available":"N/A"},{"dependency":"@parcel/transformer-sass","drift":0,"pulse":0.0027378507871321013,"releases":0,"major":0,"minor":0,"patch":0,"available":"N/A"},{"dependency":"@parcel/transformer-vue","drift":0,"pulse":0.0027378507871321013,"releases":0,"major":0,"minor":0,"patch":0,"available":"2.13.4-canary.3393"},{"dependency":"@turf/bbox","drift":0,"pulse":0.030116358658453114,"releases":0,"major":0,"minor":0,"patch":0,"available":"N/A"},{"dependency":"@turf/center-of-mass","drift":0,"pulse":0.030116358658453114,"releases":0,"major":0,"minor":0,"patch":0,"available":"N/A"},{"dependency":"@turf/line-to-polygon","drift":0,"pulse":0.030116358658453114,"releases":0,"major":0,"minor":0,"patch":0,"available":"N/A"},{"dependency":"@vue/test-utils","drift":0,"pulse":0.676249144421629,"releases":0,"major":0,"minor":0,"patch":0,"available":"N/A"},{"dependency":"@vue/vue3-jest","drift":0,"pulse":1.3415468856947297,"releases":0,"major":0,"minor":0,"patch":0,"available":"N/A"},{"dependency":"babel-jest","drift":0,"pulse":0.4188911704312115,"releases":0,"major":0,"minor":0,"patch":0,"available":"30.0.0-alpha.6"},{"dependency":"buffer","drift":0,"pulse":4.128678986995209,"releases":0,"major":0,"minor":0,"patch":0,"available":"N/A"},{"dependency":"dayjs","drift":0,"pulse":0.3860369609856263,"releases":0,"major":0,"minor":0,"patch":0,"available":"2.0.0-alpha.4"},{"dependency":"deepmerge","drift":0,"pulse":1.8179329226557153,"releases":0,"major":0,"minor":0,"patch":0,"available":"N/A"},{"dependency":"deepsortobj","drift":0,"pulse":3.184120465434634,"releases":0,"major":0,"minor":0,"patch":0,"available":"N/A"},{"dependency":"jest-cli","drift":0,"pulse":0.4188911704312115,"releases":0,"major":0,"minor":0,"patch":0,"available":"30.0.0-alpha.6"},{"dependency":"jest-environment-jsdom","drift":0,"pulse":0.4188911704312115,"releases":0,"major":0,"minor":0,"patch":0,"available":"30.0.0-alpha.6"},{"dependency":"js-yaml","drift":0,"pulse":3.7371663244353184,"releases":0,"major":0,"minor":0,"patch":0,"available":"N/A"},{"dependency":"jszip","drift":0,"pulse":2.43668720054757,"releases":0,"major":0,"minor":0,"patch":0,"available":"N/A"},{"dependency":"lodash.uniq","drift":0,"pulse":8.405201916495551,"releases":0,"major":0,"minor":0,"patch":0,"available":"N/A"},{"dependency":"maplibre-gl-indoorequal","drift":0,"pulse":0.013689253935660506,"releases":0,"major":0,"minor":0,"patch":0,"available":"N/A"},{"dependency":"maplibre-gl","drift":0,"pulse":0.02190280629705681,"releases":0,"major":0,"minor":0,"patch":0,"available":"N/A"},{"dependency":"opening_hours","drift":0,"pulse":2.64476386036961,"releases":0,"major":0,"minor":0,"patch":0,"available":"N/A"},{"dependency":"osm2geojson-lite","drift":0,"pulse":1.429158110882957,"releases":0,"major":0,"minor":0,"patch":0,"available":"N/A"},{"dependency":"parcel-reporter-static-files-copy","drift":0,"pulse":1.3032169746748803,"releases":0,"major":0,"minor":0,"patch":0,"available":"N/A"},{"dependency":"parcel-transformer-markdown-front-matter","drift":0,"pulse":0.676249144421629,"releases":0,"major":0,"minor":0,"patch":0,"available":"N/A"},{"dependency":"parcel","drift":0,"pulse":0.0027378507871321013,"releases":0,"major":0,"minor":0,"patch":0,"available":"N/A"},{"dependency":"process","drift":0,"pulse":7.704312114989733,"releases":0,"major":0,"minor":0,"patch":0,"available":"N/A"},{"dependency":"svgo","drift":0,"pulse":0.33675564681724846,"releases":0,"major":0,"minor":0,"patch":0,"available":"4.0.0-rc.1"},{"dependency":"vue-i18n","drift":0,"pulse":0.03559206023271732,"releases":0,"major":0,"minor":0,"patch":0,"available":"N/A"},{"dependency":"vue","drift":0,"pulse":0.14784394250513347,"releases":0,"major":0,"minor":0,"patch":0,"available":"N/A"},{"dependency":"vuetify","drift":0,"pulse":0.057494866529774126,"releases":0,"major":0,"minor":0,"patch":0,"available":"N/A"}]