[{"dependency":"@parcel/packager-ts","drift":0,"pulse":0.1451090713703909,"releases":0,"major":0,"minor":0,"patch":0},{"dependency":"@parcel/plugin","drift":0,"pulse":0.1451090713703909,"releases":0,"major":0,"minor":0,"patch":0},{"dependency":"@parcel/transformer-typescript-types","drift":0,"pulse":0.1451090713703909,"releases":0,"major":0,"minor":0,"patch":0},{"dependency":"@types/yaml-front-matter","drift":0,"pulse":1.7632121125005988,"releases":0,"major":0,"minor":0,"patch":0},{"dependency":"marked","drift":0,"pulse":0.024641163062896567,"releases":0,"major":0,"minor":0,"patch":0},{"dependency":"parcel","drift":0,"pulse":0.1451090713703909,"releases":0,"major":0,"minor":0,"patch":0},{"dependency":"typescript","drift":0,"pulse":0,"releases":0,"major":0,"minor":0,"patch":0},{"dependency":"yaml-front-matter","drift":0,"pulse":4.6653935399084165,"releases":0,"major":0,"minor":0,"patch":0}]