[{"dependency":"@babel/core","drift":0,"pulse":0.035592791090850597,"releases":0,"major":0,"minor":0,"patch":0},{"dependency":"@babel/preset-env","drift":0,"pulse":0.035592791090850597,"releases":0,"major":0,"minor":0,"patch":0},{"dependency":"@indoorequal/spritezero-cli","drift":0,"pulse":3.0034839866663927,"releases":0,"major":0,"minor":0,"patch":0},{"dependency":"@rollup/plugin-babel","drift":0,"pulse":0.3395004688665749,"releases":0,"major":0,"minor":0,"patch":0},{"dependency":"@rollup/plugin-commonjs","drift":0,"pulse":0.2902181427407818,"releases":0,"major":0,"minor":0,"patch":0},{"dependency":"@rollup/plugin-node-resolve","drift":0,"pulse":0.3395004688665749,"releases":0,"major":0,"minor":0,"patch":0},{"dependency":"@rollup/plugin-terser","drift":0,"pulse":2.3600758400240935,"releases":0,"major":0,"minor":0,"patch":0},{"dependency":"array-equal","drift":0,"pulse":0.8514890791734259,"releases":0,"major":0,"minor":0,"patch":0},{"dependency":"debounce","drift":0,"pulse":0.28200442171981627,"releases":0,"major":0,"minor":0,"patch":0},{"dependency":"documentation","drift":0,"pulse":2.039740720206438,"releases":0,"major":0,"minor":0,"patch":0},{"dependency":"global-jsdom","drift":0,"pulse":0.030116977076873584,"releases":0,"major":0,"minor":0,"patch":0},{"dependency":"jsdom","drift":0,"pulse":0.03285488408386209,"releases":0,"major":0,"minor":0,"patch":0},{"dependency":"rollup","drift":0,"pulse":0.03833069809783911,"releases":0,"major":0,"minor":0,"patch":0}]