[{"dependency":"@babel/core","drift":0,"pulse":0.052020233132781646,"releases":0,"major":0,"minor":0,"patch":0},{"dependency":"@babel/preset-env","drift":0,"pulse":0.052020233132781646,"releases":0,"major":0,"minor":0,"patch":0},{"dependency":"@indoorequal/spritezero-cli","drift":0,"pulse":2.5544672375202775,"releases":0,"major":0,"minor":0,"patch":0},{"dependency":"@rollup/plugin-babel","drift":0,"pulse":1.9110590908779783,"releases":0,"major":0,"minor":0,"patch":0},{"dependency":"@rollup/plugin-commonjs","drift":0,"pulse":0.2108188395381151,"releases":0,"major":0,"minor":0,"patch":0},{"dependency":"@rollup/plugin-node-resolve","drift":0,"pulse":0.47913372622298883,"releases":0,"major":0,"minor":0,"patch":0},{"dependency":"@rollup/plugin-terser","drift":0,"pulse":1.9110590908779783,"releases":0,"major":0,"minor":0,"patch":0},{"dependency":"array-equal","drift":1.3908567595501617,"pulse":0.4024723300273106,"releases":1,"major":1,"minor":0,"patch":0,"latest":"2.0.0"},{"dependency":"babel-jest","drift":0.1095162802795403,"pulse":0.005475814013977016,"releases":3,"major":0,"minor":1,"patch":2,"latest":"30.1.2"},{"dependency":"debounce","drift":0,"pulse":0.8843439632572879,"releases":0,"major":0,"minor":0,"patch":0},{"dependency":"documentation","drift":0,"pulse":1.590723971060323,"releases":0,"major":0,"minor":0,"patch":0},{"dependency":"jest-environment-jsdom","drift":0.1095162802795403,"pulse":0.005475814013977016,"releases":3,"major":0,"minor":1,"patch":2,"latest":"30.1.2"},{"dependency":"jest","drift":0.11499209429351732,"pulse":0,"releases":4,"major":0,"minor":1,"patch":3,"latest":"30.1.3"},{"dependency":"rollup","drift":0.021903256055908062,"pulse":0.005475814013977016,"releases":3,"major":0,"minor":2,"patch":1,"latest":"4.50.0"}]