[{"dependency":"@babel/types","drift":0,"pulse":0.038329911019849415,"releases":0,"major":0,"minor":0,"patch":0,"available":"8.0.0-alpha.14"},{"dependency":"@eslint/js","drift":-0.38329911019849416,"pulse":0.019164955509924708,"releases":1,"major":1,"minor":0,"patch":0,"available":"10.0.0"},{"dependency":"@maplibre/maplibre-gl-inspect","drift":0,"pulse":0.5147159479808351,"releases":0,"major":0,"minor":0,"patch":0,"available":"N/A"},{"dependency":"@mdi/js","drift":0,"pulse":0.9856262833675564,"releases":0,"major":0,"minor":0,"patch":0,"available":"N/A"},{"dependency":"@types/geojson","drift":0,"pulse":0.038329911019849415,"releases":0,"major":0,"minor":0,"patch":0,"available":"N/A"},{"dependency":"@types/jest","drift":0,"pulse":0.16153319644079397,"releases":0,"major":0,"minor":0,"patch":0,"available":"N/A"},{"dependency":"@types/node","drift":0,"pulse":0.024640657084188913,"releases":0,"major":0,"minor":0,"patch":0,"available":"N/A"},{"dependency":"@vitejs/plugin-vue","drift":0,"pulse":0.06570841889117043,"releases":0,"major":0,"minor":0,"patch":0,"available":"N/A"},{"dependency":"@vue/test-utils","drift":0,"pulse":0.6242299794661191,"releases":0,"major":0,"minor":0,"patch":0,"available":"N/A"},{"dependency":"eslint-plugin-vue","drift":0,"pulse":0.057494866529774126,"releases":0,"major":0,"minor":0,"patch":0,"available":"N/A"},{"dependency":"eslint","drift":0,"pulse":0.019164955509924708,"releases":0,"major":0,"minor":0,"patch":0,"available":"N/A"},{"dependency":"geojson","drift":0,"pulse":7.3730321697467485,"releases":0,"major":0,"minor":0,"patch":0,"available":"N/A"},{"dependency":"glob","drift":0,"pulse":0.4490075290896646,"releases":0,"major":0,"minor":0,"patch":0,"available":"N/A"},{"dependency":"globals","drift":0.04380561259411362,"pulse":0.0054757015742642025,"releases":1,"major":0,"minor":1,"patch":0,"available":"15.14.0"},{"dependency":"jest-environment-jsdom","drift":0,"pulse":0.3668720054757016,"releases":0,"major":0,"minor":0,"patch":0,"available":"30.0.0-alpha.6"},{"dependency":"jest","drift":0,"pulse":0.3668720054757016,"releases":0,"major":0,"minor":0,"patch":0,"available":"30.0.0-alpha.6"},{"dependency":"maplibre-gl","drift":0,"pulse":0.008213552361396304,"releases":0,"major":0,"minor":0,"patch":0,"available":"5.0.0-pre.10"},{"dependency":"prettier","drift":0,"pulse":0.04654346338124572,"releases":0,"major":0,"minor":0,"patch":0,"available":"4.0.0-alpha.10"},{"dependency":"sass","drift":0,"pulse":0.02190280629705681,"releases":0,"major":0,"minor":0,"patch":0,"available":"N/A"},{"dependency":"ts-jest","drift":0,"pulse":0.3258042436687201,"releases":0,"major":0,"minor":0,"patch":0,"available":"N/A"},{"dependency":"typescript-eslint","drift":0.01642710472279261,"pulse":0.008213552361396304,"releases":1,"major":0,"minor":0,"patch":1,"available":"8.18.1"},{"dependency":"typescript","drift":0,"pulse":0,"releases":0,"major":0,"minor":0,"patch":0,"available":"5.8.0-dev.20241221"},{"dependency":"vite-plugin-banner","drift":0,"pulse":0.29568788501026694,"releases":0,"major":0,"minor":0,"patch":0,"available":"N/A"},{"dependency":"vite-plugin-dts","drift":0.15605749486652978,"pulse":0.0054757015742642025,"releases":1,"major":0,"minor":1,"patch":0,"available":"4.4.0"},{"dependency":"vite","drift":0.038329911019849415,"pulse":0,"releases":2,"major":0,"minor":0,"patch":2,"available":"6.0.5"},{"dependency":"vitepress","drift":0,"pulse":0.12594113620807665,"releases":0,"major":0,"minor":0,"patch":0,"available":"N/A"},{"dependency":"vue-docgen-api","drift":0,"pulse":0.3860369609856263,"releases":0,"major":0,"minor":0,"patch":0,"available":"N/A"},{"dependency":"vue-docgen-web-types","drift":0,"pulse":2.321697467488022,"releases":0,"major":0,"minor":0,"patch":0,"available":"N/A"},{"dependency":"vue-tsc","drift":0,"pulse":0.13963039014373715,"releases":0,"major":0,"minor":0,"patch":0,"available":"N/A"},{"dependency":"vue","drift":0,"pulse":0.09582477754962354,"releases":0,"major":0,"minor":0,"patch":0,"available":"N/A"}]